test_package/__init__.py
test_package/test_module.py
test_class-0.0.2.dist-info/METADATA
test_class-0.0.2.dist-info/WHEEL
test_class-0.0.2.dist-info/top_level.txt
test_class-0.0.2.dist-info/RECORD
