Metadata-Version: 2.1
Name: test-class
Version: 0.0.2
Summary: Test Class
Classifier: Programming Language :: Python :: 3
Classifier: License :: OSI Approved :: MIT License
Classifier: Operating System :: OS Independent
Requires-Python: >=3.7
